pincer/__init__.py
pincer/_config.py
pincer/client.py
pincer/cog.py
pincer/commands/__init__.py
pincer/commands/arg_types.py
pincer/commands/chat_command_handler.py
pincer/commands/commands.py
pincer/commands/components/__init__.py
pincer/commands/components/_component.py
pincer/commands/components/action_row.py
pincer/commands/components/button.py
pincer/commands/components/component_handler.py
pincer/commands/components/decorators.py
pincer/commands/components/select_menu.py
pincer/commands/groups.py
pincer/commands/interactable.py
pincer/core/__init__.py
pincer/core/dispatch.py
pincer/core/gateway.py
pincer/core/http.py
pincer/core/ratelimiter.py
pincer/exceptions.py
pincer/middleware/__init__.py
pincer/middleware/activity_join.py
pincer/middleware/activity_join_request.py
pincer/middleware/activity_spectate.py
pincer/middleware/channel_create.py
pincer/middleware/channel_delete.py
pincer/middleware/channel_pins_update.py
pincer/middleware/channel_update.py
pincer/middleware/error.py
pincer/middleware/guild_ban_add.py
pincer/middleware/guild_ban_remove.py
pincer/middleware/guild_create.py
pincer/middleware/guild_delete.py
pincer/middleware/guild_emojis_update.py
pincer/middleware/guild_integrations_update.py
pincer/middleware/guild_member_add.py
pincer/middleware/guild_member_remove.py
pincer/middleware/guild_member_update.py
pincer/middleware/guild_members_chunk.py
pincer/middleware/guild_role_create.py
pincer/middleware/guild_role_delete.py
pincer/middleware/guild_role_update.py
pincer/middleware/guild_status.py
pincer/middleware/guild_stickers_update.py
pincer/middleware/guild_update.py
pincer/middleware/integration_create.py
pincer/middleware/integration_delete.py
pincer/middleware/integration_update.py
pincer/middleware/interaction_create.py
pincer/middleware/invite_create.py
pincer/middleware/invite_delete.py
pincer/middleware/message_create.py
pincer/middleware/message_delete.py
pincer/middleware/message_delete_bulk.py
pincer-0.16.1.dist-info/LICENSE
pincer-0.16.1.dist-info/WHEEL
pincer-0.16.1.dist-info/METADATA
pincer-0.16.1.dist-info/RECORD
