Metadata-Version: 2.1
Name: pincer
Version: 0.16.1
Summary: Discord API wrapper rebuilt from scratch.
Home-page: https://pincer.dev
License: MIT
Keywords: discord,api,asynchronous,websockets,aiohttp
Author: Pincer-org
Author-email: contact@pincer.dev
Requires-Python: >=3.8,<3.11
Classifier: Development Status :: 3 - Alpha
Classifier: Intended Audience :: Developers
Classifier: License :: OSI Approved :: MIT License
Classifier: Programming Language :: Python :: 3
Classifier: Programming Language :: Python :: 3 :: Only
Classifier: Programming Language :: Python :: 3.10
Classifier: Programming Language :: Python :: 3.8
Classifier: Programming Language :: Python :: 3.9
Classifier: Topic :: Software Development :: Build Tools
Provides-Extra: img
Provides-Extra: speed
Requires-Dist: Brotli (>=1.0.9,<2.0.0); extra == "speed"
Requires-Dist: Pillow (>=9.2.0,<10.0.0); extra == "img"
Requires-Dist: aiodns (>=3.0.0,<4.0.0); extra == "speed"
Requires-Dist: aiohttp (>=3.8.1,<4.0.0)
Requires-Dist: cchardet (>=2.1.7,<3.0.0); extra == "speed"
Requires-Dist: orjson (>=3.7.11,<4.0.0); extra == "speed"
Requires-Dist: types-Pillow (>=9.2.1,<10.0.0); extra == "img"
Project-URL: Documentation, https://docs.pincer.dev
Project-URL: Discord, https://discord.gg/8WkYz3fNFm
Project-URL: Repository, https://github.com/Pincer-org/Pincer
